{"programme":{"type":"episode","pid":"p00yjnpl","expected_child_count":null,"position":null,"image":{"pid":"p01vzv4w"},"media_type":"audio","title":"Saddam\u0027s nuclear arsenal","short_synopsis":"A discussion on America\u0027s possible reaction to Saddam Hussein\u0027s nuclear stockpile.","medium_synopsis":"How can America deal with Saddam Hussein\u0027s suspected nuclear and biological weapons in Iraq and does a resurgence in US financial markets conceal an unstable future?","long_synopsis":null,"first_broadcast_date":"1998-11-27T21:00:00Z","display_title":{"title":"Letter from America by Alistair Cooke","subtitle":"Saddam\u0027s nuclear arsenal"},"parent":{"programme":{"type":"brand","pid":"b00f6hbp","title":"Letter from America by Alistair Cooke","short_synopsis":"Alistair Cooke\u2019s weekly talks on American life, history and politics from 1946 \u2013 2004.","position":null,"image":{"pid":"p01vzv4w"},"expected_child_count":null,"first_broadcast_date":"1947-01-12T21:00:00Z","aggregated_episode_count":1601,"ownership":{"service":{"type":"radio","id":"bbc_radio_four","key":"radio4","title":"BBC Radio 4"}}}},"peers":{"previous":{"type":"episode","pid":"p00yjnqv","title":"Some memorable letters from America","first_broadcast_date":"1998-11-20T21:00:00Z","position":null,"media_type":"audio"},"next":{"type":"episode","pid":"p00yjnmz","title":"Thanksgiving 1998","first_broadcast_date":"1998-12-04T21:00:00Z","position":null,"media_type":"audio"}},"versions":[{"canonical":1,"pid":"p00yjnpn","duration":900,"types":["Original version"]},{"canonical":0,"pid":"p02qc66g","duration":853,"types":["Podcast version"]}],"links":[],"supporting_content_items":[],"categories":[{"type":"genre","id":"C00046","key":"artscultureandthemedia","title":"Arts, Culture \u0026 the Media","narrower":[],"broader":{"category":{"type":"genre","id":"C00045","key":"factual","title":"Factual","broader":{},"has_topic_page":false,"sameAs":null}},"has_topic_page":false,"sameAs":null}]}}